Metadata-Version: 1.0
Name: myownpypipackage
Version: 0.0.1
Summary: paquete de prueba
Home-page: https://github.com/robcg1102/pypipackage
Author: Roberto Carro Gastélum
Author-email: UNKNOWN
License: MIT
Platform: UNKNOWN
